{
  "url": "https://developer.chrome.com/deprecated",
  "title": "Chrome Archive \u00a0|\u00a0 Build with Chrome \u00a0|\u00a0 Chrome for Developers",
  "description": "",
  "content_type": "how_to",
  "taxonomies": {
    "language": [
      "go",
      "c++"
    ],
    "platform": [
      "android",
      "web"
    ]
  },
  "entities": {
    "code_references": [
      "url",
      "function",
      "getElementsByTagName",
      "insertBefore",
      "var",
      "createElement"
    ],
    "api_endpoints": [],
    "file_extensions": [
      "apps",
      "35",
      "825",
      "3917",
      "9C20",
      "web",
      "7C7",
      "8C15",
      "5167",
      "8583"
    ],
    "command_names": []
  },
  "version": null,
  "last_updated": null,
  "word_count": 3699,
  "code_blocks_count": 0,
  "heading_count": 7,
  "link_count": 82,
  "image_count": 2,
  "keywords": [
    "devsite",
    "class",
    "track",
    "metadata",
    "chrome",
    "https",
    "href",
    "data",
    "item",
    "docs",
    "developer",
    "null",
    "link",
    "role",
    "span",
    "type",
    "label",
    "tooltip",
    "position",
    "title"
  ],
  "reading_time": 18,
  "complexity_score": 4.4,
  "metadata_generated": "2026-01-07T02:01:31.362973"
}